cloudshell/__init__.py
cloudshell/calix/__init__.py
cloudshell/calix/autoload/__init__.py
cloudshell/calix/autoload/calix_entity_table.py
cloudshell/calix/autoload/calix_generic_snmp_autoload.py
cloudshell/calix/autoload/snmp_system_info.py
cloudshell/calix/cli/__init__.py
cloudshell/calix/cli/calix_cli_handler.py
cloudshell/calix/cli/calix_command_modes.py
cloudshell/calix/command_actions/__init__.py
cloudshell/calix/command_actions/enable_disable_snmp_actions.py
cloudshell/calix/command_actions/save_restore_actions.py
cloudshell/calix/command_actions/system_actions.py
cloudshell/calix/command_templates/__init__.py
cloudshell/calix/command_templates/configuration.py
cloudshell/calix/command_templates/enable_disable_snmp.py
cloudshell/calix/command_templates/system.py
cloudshell/calix/flows/__init__.py
cloudshell/calix/flows/calix_autoload_flow.py
cloudshell/calix/flows/calix_configuration_flow.py
cloudshell/calix/flows/calix_disable_snmp_flow.py
cloudshell/calix/flows/calix_enable_snmp_flow.py
cloudshell/calix/flows/calix_run_command_flow.py
cloudshell/calix/flows/calix_state_flow.py
cloudshell/calix/helpers/__init__.py
cloudshell/calix/helpers/exceptions.py
cloudshell/calix/mibs/Axos-Card-MIB.py
cloudshell/calix/mibs/Axos-System-MIB.py
cloudshell/calix/mibs/CALIX-PRODUCT-MIB.py
cloudshell/calix/mibs/CALIX-SMI.py
cloudshell/calix/mibs/__init__.py
cloudshell/calix/snmp/__init__.py
cloudshell/calix/snmp/calix_snmp_handler.py
tests/__init__.py
tests/cloudshell/__init__.py
tests/cloudshell/calix/__init__.py
tests/cloudshell/calix/cli/__init__.py
tests/cloudshell/calix/cli/test_cli_handler.py
cloudshell_calix-0.2.5.dist-info/METADATA
cloudshell_calix-0.2.5.dist-info/WHEEL
cloudshell_calix-0.2.5.dist-info/top_level.txt
cloudshell_calix-0.2.5.dist-info/RECORD
