Metadata-Version: 2.1
Name: cloudshell-calix
Version: 0.2.5
Summary: QualiSystems networking Calix specific package
Home-page: http://www.qualisystems.com/
Author: QualiSystems
Author-email: info@qualisystems.com
Requires-Python: ~=3.7
Requires-Dist: cloudshell-shell-flows (<2.0,>=1.0)
Requires-Dist: cloudshell-snmp (<5.0,>=4.0)
Requires-Dist: cloudshell-snmp-autoload (<2.0,>=1.0)
Requires-Dist: cloudshell-cli (<5.0,>=4.0)
Requires-Dist: retrying (~=1.3.3)
